wisepaasscadasdk/EdgeAgent.py
wisepaasscadasdk/__init__.py
wisepaasscadasdk/Common/Constants.py
wisepaasscadasdk/Common/Converter.py
wisepaasscadasdk/Common/DataRecoverHelper.py
wisepaasscadasdk/Common/Topic.py
wisepaasscadasdk/Common/Utils.py
wisepaasscadasdk/Common/__init__.py
wisepaasscadasdk/Model/Edge.py
wisepaasscadasdk/Model/Event.py
wisepaasscadasdk/Model/MQTTMessage.py
wisepaasscadasdk/Model/__init__.py
WISE_PaaS_SCADA_Python_SDK-1.0.10.dist-info/METADATA
WISE_PaaS_SCADA_Python_SDK-1.0.10.dist-info/WHEEL
WISE_PaaS_SCADA_Python_SDK-1.0.10.dist-info/top_level.txt
WISE_PaaS_SCADA_Python_SDK-1.0.10.dist-info/RECORD
