Metadata-Version: 2.1
Name: WISE-PaaS-SCADA-Python-SDK
Version: 1.0.10
Summary: The WISEPaaS_SCADA_Python_SDK package allows developers to write Python applications which access the WISE-PaaS Platform via MQTT or MQTT over the Secure WebSocket Protocol.
Home-page: https://github.com/advwacloud/WISEPaaS.SCADA.Python.SDK
Author: Stacy Yeh
Author-email: stacy.yeh@advantech.com
License: UNKNOWN
Platform: UNKNOWN
Classifier: Programming Language :: Python :: 3
Requires-Dist: paho-mqtt (==1.4.0)
